bs_monitoring/__init__.py
bs_monitoring/alert_services/__init__.py
bs_monitoring/alert_services/base.py
bs_monitoring/alert_services/opsgenie.py
bs_monitoring/common/__init__.py
bs_monitoring/common/utils.py
bs_monitoring/common/configs/__init__.py
bs_monitoring/common/configs/base.py
bs_monitoring/data_sources/__init__.py
bs_monitoring/data_sources/base.py
bs_monitoring/data_sources/elastic.py
bs_monitoring/databases/__init__.py
bs_monitoring/databases/base.py
bs_monitoring/databases/postgres.py
bs_monitoring/databases/sqlite.py
bs_monitoring/monitors/__init__.py
bs_monitoring/monitors/base.py
bs_monitoring/monitors/data_quantity.py
bs_monitoring/monitors/data_scheme.py
bs_monitoring-1.0.1.dist-info/LICENSE
bs_monitoring-1.0.1.dist-info/METADATA
bs_monitoring-1.0.1.dist-info/WHEEL
bs_monitoring-1.0.1.dist-info/top_level.txt
bs_monitoring-1.0.1.dist-info/RECORD
