Metadata-Version: 2.1
Name: bs_monitoring
Version: 1.0.1
Summary: A simple monitoring tool-kit enabling easier description of monitoring data pipelines.
Author-email: Matej Sirovatka <matej.sirovatka@gmail.com>
License: MIT
Project-URL: Homepage, https://github.com/bitswan-space/bs-monitoring
Classifier: Programming Language :: Python :: 3
Classifier: License :: OSI Approved :: MIT License
Classifier: Operating System :: OS Independent
License-File: LICENSE
Requires-Dist: elasticsearch<9,>=8.12.1
Requires-Dist: python-dotenv
Requires-Dist: psycopg2<3,>=2.9.9
Requires-Dist: dacite==1.8.1
Requires-Dist: Cerberus==1.3.5
Requires-Dist: pytz<2025,>=2024.1
